flardl-0.0.8.2.dist-info/METADATA
flardl-0.0.8.2.dist-info/WHEEL
flardl-0.0.8.2.dist-info/licenses/LICENSE
flardl-0.0.8.2.dist-info/licenses/LICENSE.logo.txt
flardl/__init__.py
flardl/common.py
flardl/dict_to_indexed_list.py
flardl/downloader.py
flardl/instrumented_streams.py
flardl/multidispatcher.py
flardl/py.typed
flardl/server_defs.py
flardl/stream_stats.py
flardl-0.0.8.2.dist-info/RECORD
