Metadata-Version: 2.1
Name: flardl
Version: 0.0.8.2
Summary: Adaptive Elastic Multi-Site Downloading
Keywords: downloading asynchronous multidispatching queueing adaptive elastic adaptilastic federated high-performance
Author-Email: Joel Berendzen <joel@generisbio.com>
License: BSD-3-Clause
Classifier: Development Status :: 3 - Alpha
Classifier: Environment :: Console
Classifier: Intended Audience :: Developers
Classifier: License :: OSI Approved :: BSD License
Classifier: Natural Language :: English
Classifier: Operating System :: OS Independent
Classifier: Programming Language :: Python :: 3.9
Classifier: Programming Language :: Python :: 3.10
Classifier: Programming Language :: Python :: 3.11
Classifier: Programming Language :: Python :: 3.12
Classifier: Topic :: Internet :: WWW/HTTP
Requires-Python: <3.13,>=3.9
Requires-Dist: anyio>=4.0.0
Requires-Dist: attrs>=23.1.0
Requires-Dist: httpx[http2]>=0.25.1
Requires-Dist: tqdm>=4.66.1
Requires-Dist: trio>=0.23.1
Requires-Dist: psutil>=5.9.6
Requires-Dist: uvloop>=0.19.0; platform_system != "Windows"
Requires-Dist: typer>=0.9.0; extra == "analysis"
Requires-Dist: scipy>=1.11.4; extra == "analysis"
Requires-Dist: seaborn>=0.13.1; extra == "analysis"
Provides-Extra: analysis
